README.txt
setup.py
dogbutler/__init__.py
dogbutler/api.py
dogbutler/async.py
dogbutler/cache.py
dogbutler/cookie.py
dogbutler/defaults.py
dogbutler/models.py
dogbutler/redirect.py
dogbutler/sessions.py
dogbutler.egg-info/PKG-INFO
dogbutler.egg-info/SOURCES.txt
dogbutler.egg-info/dependency_links.txt
dogbutler.egg-info/requires.txt
dogbutler.egg-info/top_level.txt
dogbutler/tests/__init__.py
dogbutler/tests/base.py
dogbutler/tests/datetimestub.py
dogbutler/tests/test_api.py
dogbutler/tests/test_async.py
dogbutler/tests/test_cache.py
dogbutler/tests/test_cookie.py
dogbutler/tests/test_defaults.py
dogbutler/tests/test_sessions.py
dogbutler/utils/__init__.py
dogbutler/utils/cache.py
dogbutler/utils/encoding.py
dogbutler/utils/functional.py
dogbutler/utils/hashcompat.py
dogbutler/utils/rand.py
setup/requirements.txt