Metadata-Version: 1.0
Name: dogbutler
Version: 0.0.4
Summary: Make HTTP/HTTPS requests with cache, cookie, and redirect support
Home-page: http://code.google.com/p/dogbutler/
Author: The Sirisanthana Team
Author-email: vsirisanthana@gmail.com
License: GPL-3.0
Download-URL: http://pypi.python.org/pypi/dogbutler
Keywords: HTTP HTTPS request python cache cookie redirect
Platform: UNKNOWN
Classifier: Development Status :: 3 - Alpha
Classifier: Intended Audience :: Developers
Classifier: Programming Language :: Python
Classifier: Topic :: Software Development :: Libraries :: Python Modules
Classifier: License :: OSI Approved :: GNU General Public License (GPL)
